[
  {
    "id": "6200e9fd-d551-4b91-85ec-ee30fb179a32",
    "data": [
      {
        "text": "fine work",
        "userDefined": false
      }
    ],
    "isTemplate": false,
    "count": 0,
    "updated": 0
  },
  {
    "id": "c260072f-3332-47d7-b143-779eeb85515b",
    "data": [
      {
        "text": "thankyou so much",
        "userDefined": false
      }
    ],
    "isTemplate": false,
    "count": 0,
    "updated": 0
  },
  {
    "id": "eb504922-f916-4263-a14d-442fca347940",
    "data": [
      {
        "text": "good",
        "userDefined": false
      }
    ],
    "isTemplate": false,
    "count": 0,
    "updated": 0
  },
  {
    "id": "2c06c4e0-6dd8-4d09-b057-b2a8b5676e1a",
    "data": [
      {
        "text": "youre great",
        "userDefined": false
      }
    ],
    "isTemplate": false,
    "count": 0,
    "updated": 0
  },
  {
    "id": "76c032ca-8652-4b05-b602-0b44d773cf10",
    "data": [
      {
        "text": "Thankyou",
        "userDefined": false
      }
    ],
    "isTemplate": false,
    "count": 0,
    "updated": 0
  }
]